<?xml version="1.0" encoding="utf-8"?><index><!-- saved from url=(0016)http://localhost -->
<stem n="simpli"><phr n="simply"><ent r="7" t="10" w="251" /><ent r="7" t="10" w="251" /><ent r="3" t="60" w="595" /><ent r="3" t="60" w="595" /><ent r="3" t="2595" w="187" /><ent r="3" t="2595" w="187" /></phr></stem><stem n="compens"><phr n="compensate"><ent r="7" t="10" w="259" /><ent r="7" t="10" w="259" /><ent r="3" t="2781" w="58" /><ent r="3" t="2781" w="58" /></phr><phr n="compensated"><ent r="3" t="23" w="1006" /><ent r="3" t="23" w="1006" /><ent r="3" t="117" w="65" /><ent r="3" t="117" w="65" /><ent r="3" t="468" w="43" /><ent r="3" t="468" w="43" /></phr><phr n="compensating"><ent r="3" t="104" w="377" /><ent r="3" t="104" w="377" /><ent r="4" t="1026" w="121" /><ent r="4" t="1026" w="121" /><ent r="3" t="3004" w="114" /><ent r="3" t="3004" w="114" /></phr><phr n="compensates"><ent r="3" t="136" w="42" /><ent r="3" t="136" w="42" /><ent r="3" t="136" w="62" /><ent r="3" t="136" w="62" /><ent r="3" t="152" w="238" /><ent r="3" t="152" w="238" /><ent r="3" t="152" w="282" /><ent r="3" t="152" w="282" /><ent r="3" t="153" w="501" /><ent r="3" t="153" w="501" /><ent r="3" t="153" w="524" /><ent r="3" t="153" w="524" /><ent r="3" t="154" w="394" /><ent r="3" t="154" w="394" /><ent r="3" t="154" w="438" /><ent r="3" t="154" w="438" /><ent r="7" t="181" w="54" /><ent r="7" t="181" w="54" /><ent r="7" t="181" w="185" /><ent r="7" t="181" w="185" /><ent r="3" t="182" w="351" /><ent r="3" t="182" w="351" /><ent r="3" t="182" w="395" /><ent r="3" t="182" w="395" /></phr><phr n="Compensates"><ent r="3" t="158" w="271" /><ent r="3" t="158" w="271" /></phr><phr n="compensation"><ent r="3" t="642" w="26" /><ent r="1000" t="643" w="5" /><ent r="1000" t="643" w="5" /><ent r="92" t="643" w="13" /><ent r="92" t="643" w="13" /><ent r="3" t="643" w="23" /><ent r="3" t="644" w="23" /><ent r="3" t="647" w="20" /><ent r="3" t="647" w="20" /><ent r="3" t="647" w="35" /><ent r="3" t="648" w="23" /><ent r="3" t="649" w="23" /><ent r="1000" t="924" w="8" /><ent r="92" t="924" w="22" /><ent r="1000" t="2463" w="4" /><ent r="1000" t="2463" w="4" /><ent r="92" t="2463" w="14" /><ent r="92" t="2463" w="14" /></phr><phr n="Compensation"><ent r="1000" t="647" w="2" /><ent r="1000" t="647" w="2" /><ent r="92" t="647" w="12" /><ent r="92" t="647" w="12" /></phr></stem><stem n="misalign"><phr n="misalignment"><ent r="7" t="10" w="262" /><ent r="7" t="10" w="262" /></phr><phr n="misaligned"><ent r="3" t="2285" w="34" /></phr></stem><stem n="control"><phr n="controlled"><ent r="3" t="10" w="316" /><ent r="3" t="10" w="316" /><ent r="4" t="60" w="283" /><ent r="1000" t="816" w="11" /><ent r="1000" t="816" w="11" /><ent r="92" t="816" w="25" /><ent r="92" t="816" w="25" /><ent r="1000" t="817" w="11" /><ent r="92" t="817" w="25" /><ent r="1000" t="818" w="13" /><ent r="92" t="818" w="29" /><ent r="3" t="825" w="32" /><ent r="3" t="944" w="27" /><ent r="3" t="2734" w="51" /><ent r="3" t="2734" w="51" /><ent r="3" t="2833" w="184" /><ent r="3" t="2833" w="184" /><ent r="3" t="3165" w="21" /><ent r="3" t="3165" w="21" /></phr><phr n="controls"><ent r="3" t="27" w="50" /><ent r="3" t="27" w="50" /><ent r="3" t="27" w="98" /><ent r="3" t="27" w="98" /><ent r="3" t="104" w="328" /><ent r="3" t="104" w="340" /><ent r="3" t="104" w="340" /><ent r="3" t="107" w="187" /><ent r="3" t="107" w="187" /><ent r="3" t="107" w="256" /><ent r="3" t="107" w="256" /><ent r="7" t="108" w="99" /><ent r="7" t="108" w="99" /><ent r="3" t="110" w="113" /><ent r="3" t="110" w="113" /><ent r="3" t="110" w="181" /><ent r="3" t="110" w="237" /><ent r="3" t="110" w="237" /><ent r="3" t="2305" w="21" /><ent r="3" t="2305" w="21" /><ent r="3" t="2609" w="27" /><ent r="3" t="3059" w="140" /><ent r="3" t="3059" w="140" /><ent r="3" t="3059" w="222" /><ent r="3" t="3059" w="222" /><ent r="3" t="3060" w="140" /><ent r="3" t="3060" w="140" /><ent r="3" t="3060" w="173" /><ent r="3" t="3060" w="173" /><ent r="3" t="3062" w="55" /><ent r="3" t="3062" w="55" /><ent r="3" t="3063" w="74" /><ent r="3" t="3063" w="74" /><ent r="3" t="3086" w="130" /><ent r="3" t="3086" w="130" /><ent r="4" t="3136" w="137" /><ent r="4" t="3136" w="150" /><ent r="4" t="3136" w="150" /><ent r="3" t="3137" w="113" /><ent r="3" t="3137" w="113" /><ent r="3" t="3145" w="88" /><ent r="4" t="3146" w="141" /><ent r="4" t="3146" w="154" /><ent r="4" t="3146" w="154" /><ent r="3" t="3146" w="169" /><ent r="3" t="3146" w="179" /><ent r="3" t="3148" w="88" /></phr><phr n="control"><ent r="3" t="52" w="75" /><ent r="3" t="52" w="75" /><ent r="3" t="52" w="108" /><ent r="3" t="52" w="108" /><ent r="3" t="56" w="235" /><ent r="3" t="56" w="235" /><ent r="3" t="99" w="17" /><ent r="3" t="99" w="17" /><ent r="3" t="100" w="93" /><ent r="3" t="100" w="93" /><ent r="3" t="100" w="154" /><ent r="3" t="100" w="154" /><ent r="3" t="101" w="214" /><ent r="3" t="101" w="214" /><ent r="3" t="153" w="161" /><ent r="3" t="153" w="161" /><ent r="3" t="153" w="217" /><ent r="3" t="153" w="217" /><ent r="3" t="153" w="244" /><ent r="3" t="153" w="244" /><ent r="3" t="153" w="255" /><ent r="3" t="153" w="255" /><ent r="3" t="153" w="260" /><ent r="3" t="153" w="260" /><ent r="7" t="181" w="413" /><ent r="7" t="181" w="413" /><ent r="7" t="181" w="424" /><ent r="7" t="181" w="424" /><ent r="7" t="181" w="429" /><ent r="7" t="181" w="429" /><ent r="7" t="181" w="510" /><ent r="7" t="181" w="510" /><ent r="7" t="181" w="555" /><ent r="7" t="181" w="555" /><ent r="3" t="297" w="30" /><ent r="3" t="297" w="30" /><ent r="3" t="298" w="157" /><ent r="3" t="298" w="157" /><ent r="3" t="387" w="36" /><ent r="3" t="387" w="36" /><ent r="3" t="388" w="32" /><ent r="3" t="388" w="32" /><ent r="3" t="398" w="39" /><ent r="3" t="398" w="39" /><ent r="1000" t="416" w="4" /><ent r="1000" t="416" w="4" /><ent r="92" t="416" w="15" /><ent r="92" t="416" w="15" /><ent r="3" t="435" w="18" /><ent r="3" t="435" w="18" /><ent r="3" t="445" w="24" /><ent r="3" t="445" w="24" /><ent r="3" t="445" w="40" /><ent r="3" t="445" w="40" /><ent r="3" t="453" w="22" /><ent r="3" t="453" w="22" /><ent r="3" t="453" w="38" /><ent r="3" t="453" w="38" /><ent r="1000" t="471" w="6" /><ent r="1000" t="471" w="6" /><ent r="92" t="471" w="16" /><ent r="92" t="471" w="16" /><ent r="1000" t="481" w="6" /><ent r="1000" t="481" w="6" /><ent r="92" t="481" w="18" /><ent r="92" t="481" w="18" /><ent r="1000" t="513" w="3" /><ent r="1000" t="513" w="3" /><ent r="92" t="513" w="16" /><ent r="92" t="513" w="16" /><ent r="3" t="513" w="27" /><ent r="3" t="513" w="27" /><ent r="5" t="513" w="60" /><ent r="5" t="513" w="60" /><ent r="3" t="513" w="129" /><ent r="3" t="513" w="129" /><ent r="3" t="825" w="35" /><ent r="3" t="825" w="35" /><ent r="3" t="918" w="43" /><ent r="3" t="918" w="43" /><ent r="1000" t="928" w="8" /><ent r="1000" t="928" w="8" /><ent r="92" t="928" w="20" /><ent r="92" t="928" w="20" /><ent r="3" t="1258" w="128" /><ent r="3" t="1315" w="26" /><ent r="3" t="1315" w="26" /><ent r="1000" t="1327" w="9" /><ent r="1000" t="1327" w="9" /><ent r="93" t="1327" w="25" /><ent r="93" t="1327" w="25" /><ent r="3" t="1430" w="63" /><ent r="3" t="1430" w="63" /><ent r="1000" t="1640" w="9" /><ent r="1000" t="1640" w="9" /><ent r="92" t="1640" w="22" /><ent r="92" t="1640" w="22" /><ent r="1000" t="1645" w="11" /><ent r="1000" t="1645" w="11" /><ent r="92" t="1645" w="27" /><ent r="92" t="1645" w="27" /><ent r="3" t="1686" w="35" /><ent r="3" t="1686" w="35" /><ent r="3" t="1810" w="30" /><ent r="3" t="1810" w="30" /><ent r="3" t="1840" w="33" /><ent r="3" t="1840" w="33" /><ent r="3" t="1840" w="46" /><ent r="3" t="1840" w="46" /><ent r="1000" t="1870" w="5" /><ent r="1000" t="1870" w="5" /><ent r="92" t="1870" w="17" /><ent r="92" t="1870" w="17" /><ent r="1000" t="1877" w="6" /><ent r="1000" t="1877" w="6" /><ent r="92" t="1877" w="20" /><ent r="92" t="1877" w="20" /><ent r="1000" t="1878" w="6" /><ent r="1000" t="1878" w="6" /><ent r="92" t="1878" w="20" /><ent r="92" t="1878" w="20" /><ent r="3" t="1893" w="21" /><ent r="3" t="1893" w="21" /><ent r="3" t="1894" w="21" /><ent r="3" t="1894" w="21" /><ent r="1000" t="2005" w="6" /><ent r="92" t="2005" w="17" /><ent r="1000" t="2052" w="4" /><ent r="1000" t="2052" w="4" /><ent r="92" t="2052" w="13" /><ent r="92" t="2052" w="13" /><ent r="4" t="2052" w="25" /><ent r="4" t="2052" w="25" /><ent r="1000" t="2181" w="5" /><ent r="1000" t="2181" w="5" /><ent r="92" t="2181" w="15" /><ent r="92" t="2181" w="15" /><ent r="3" t="2389" w="36" /><ent r="3" t="2389" w="36" /><ent r="4" t="2389" w="43" /><ent r="4" t="2389" w="43" /><ent r="1000" t="2450" w="3" /><ent r="1000" t="2450" w="3" /><ent r="92" t="2450" w="20" /><ent r="92" t="2450" w="20" /><ent r="1000" t="2476" w="8" /><ent r="1000" t="2476" w="8" /><ent r="92" t="2476" w="23" /><ent r="92" t="2476" w="23" /><ent r="1000" t="2477" w="11" /><ent r="1000" t="2477" w="11" /><ent r="92" t="2477" w="26" /><ent r="92" t="2477" w="26" /><ent r="3" t="2536" w="21" /><ent r="3" t="2536" w="21" /><ent r="1000" t="2602" w="3" /><ent r="1000" t="2602" w="3" /><ent r="100" t="2602" w="8" /><ent r="100" t="2602" w="8" /><ent r="102" t="2602" w="13" /><ent r="102" t="2602" w="13" /><ent r="3" t="2602" w="27" /><ent r="3" t="2602" w="27" /><ent r="3" t="2611" w="25" /><ent r="3" t="2795" w="48" /><ent r="3" t="2795" w="48" /><ent r="3" t="2795" w="64" /><ent r="3" t="2795" w="64" /><ent r="3" t="2796" w="59" /><ent r="3" t="2796" w="59" /><ent r="3" t="2796" w="68" /><ent r="3" t="2796" w="68" /><ent r="3" t="2796" w="81" /><ent r="3" t="2796" w="81" /><ent r="3" t="2822" w="132" /><ent r="3" t="2822" w="132" /><ent r="4" t="2823" w="209" /><ent r="4" t="2823" w="209" /><ent r="5" t="2930" w="73" /><ent r="5" t="2930" w="73" /><ent r="7" t="3105" w="94" /><ent r="7" t="3105" w="94" /><ent r="7" t="3105" w="294" /><ent r="7" t="3105" w="294" /><ent r="3" t="3107" w="33" /><ent r="3" t="3107" w="33" /></phr><phr n="controller"><ent r="3" t="78" w="350" /><ent r="3" t="78" w="350" /><ent r="3" t="83" w="190" /><ent r="3" t="137" w="70" /><ent r="3" t="137" w="70" /><ent r="3" t="193" w="446" /><ent r="3" t="196" w="346" /><ent r="1000" t="488" w="6" /><ent r="1000" t="488" w="6" /><ent r="92" t="488" w="15" /><ent r="92" t="488" w="15" /><ent r="3" t="511" w="29" /><ent r="3" t="560" w="50" /><ent r="3" t="561" w="46" /><ent r="7" t="817" w="151" /><ent r="7" t="817" w="151" /><ent r="3" t="1683" w="16" /><ent r="3" t="1683" w="16" /><ent r="1000" t="1811" w="4" /><ent r="1000" t="1811" w="4" /><ent r="92" t="1811" w="14" /><ent r="92" t="1811" w="14" /><ent r="3" t="1811" w="31" /><ent r="1000" t="1814" w="11" /><ent r="1000" t="1814" w="11" /><ent r="92" t="1814" w="28" /><ent r="92" t="1814" w="28" /><ent r="3" t="1814" w="44" /><ent r="3" t="1814" w="44" /><ent r="3" t="1814" w="81" /><ent r="3" t="1814" w="89" /><ent r="3" t="1818" w="24" /><ent r="3" t="1818" w="24" /><ent r="3" t="1822" w="61" /><ent r="3" t="1840" w="60" /><ent r="3" t="1870" w="26" /><ent r="3" t="1870" w="26" /><ent r="3" t="1876" w="47" /><ent r="3" t="1876" w="47" /><ent r="3" t="1877" w="54" /><ent r="3" t="1877" w="54" /><ent r="3" t="1884" w="105" /><ent r="3" t="1884" w="105" /><ent r="3" t="1884" w="114" /><ent r="3" t="1889" w="47" /><ent r="3" t="1889" w="47" /><ent r="3" t="1890" w="37" /><ent r="3" t="1890" w="37" /><ent r="3" t="1890" w="52" /><ent r="3" t="1890" w="70" /><ent r="3" t="1890" w="70" /><ent r="3" t="1893" w="34" /><ent r="3" t="1894" w="34" /><ent r="3" t="1905" w="89" /><ent r="3" t="1905" w="96" /><ent r="3" t="1906" w="88" /><ent r="3" t="1906" w="88" /><ent r="3" t="1906" w="95" /><ent r="6" t="1980" w="167" /><ent r="6" t="1980" w="167" /><ent r="5" t="1992" w="18" /><ent r="5" t="1993" w="17" /><ent r="5" t="1993" w="20" /><ent r="5" t="1993" w="20" /><ent r="3" t="2031" w="30" /><ent r="3" t="2032" w="30" /><ent r="3" t="2085" w="30" /><ent r="3" t="2181" w="53" /><ent r="3" t="2181" w="53" /><ent r="3" t="2182" w="54" /><ent r="3" t="2182" w="54" /><ent r="3" t="2182" w="63" /><ent r="3" t="2182" w="63" /><ent r="1000" t="2183" w="9" /><ent r="1000" t="2183" w="9" /><ent r="92" t="2183" w="21" /><ent r="92" t="2183" w="21" /><ent r="3" t="2183" w="62" /><ent r="3" t="2183" w="62" /><ent r="3" t="2183" w="71" /><ent r="3" t="2183" w="71" /><ent r="1000" t="2184" w="7" /><ent r="1000" t="2184" w="7" /><ent r="92" t="2184" w="17" /><ent r="92" t="2184" w="17" /><ent r="3" t="2184" w="63" /><ent r="3" t="2184" w="63" /><ent r="3" t="2184" w="72" /><ent r="3" t="2184" w="72" /><ent r="1000" t="2185" w="7" /><ent r="1000" t="2185" w="7" /><ent r="92" t="2185" w="19" /><ent r="92" t="2185" w="19" /><ent r="3" t="2185" w="50" /><ent r="3" t="2185" w="50" /><ent r="3" t="2185" w="59" /><ent r="3" t="2185" w="59" /><ent r="3" t="2186" w="62" /><ent r="3" t="2186" w="62" /><ent r="3" t="2186" w="71" /><ent r="3" t="2186" w="71" /><ent r="3" t="2187" w="66" /><ent r="3" t="2187" w="66" /><ent r="3" t="2187" w="75" /><ent r="3" t="2187" w="75" /><ent r="1000" t="2188" w="7" /><ent r="1000" t="2188" w="7" /><ent r="92" t="2188" w="17" /><ent r="92" t="2188" w="17" /><ent r="3" t="2188" w="25" /><ent r="3" t="2188" w="25" /><ent r="3" t="2188" w="52" /><ent r="3" t="2188" w="52" /><ent r="3" t="2188" w="61" /><ent r="3" t="2188" w="61" /><ent r="3" t="2195" w="27" /><ent r="3" t="2195" w="27" /><ent r="3" t="2196" w="130" /><ent r="3" t="2196" w="130" /><ent r="3" t="2197" w="128" /><ent r="3" t="2197" w="128" /><ent r="3" t="2198" w="17" /><ent r="3" t="2198" w="17" /><ent r="3" t="2568" w="19" /><ent r="3" t="2568" w="19" /><ent r="3" t="2568" w="37" /><ent r="3" t="2568" w="37" /><ent r="1000" t="2569" w="5" /><ent r="1000" t="2569" w="5" /><ent r="92" t="2569" w="13" /><ent r="92" t="2569" w="13" /><ent r="1000" t="2570" w="3" /><ent r="1000" t="2570" w="3" /><ent r="92" t="2570" w="12" /><ent r="92" t="2570" w="12" /><ent r="7" t="2809" w="148" /><ent r="7" t="2809" w="157" /><ent r="7" t="2809" w="161" /><ent r="7" t="2809" w="161" /><ent r="7" t="3041" w="88" /><ent r="7" t="3041" w="88" /></phr><phr n="Control"><ent r="3" t="846" w="55" /><ent r="3" t="846" w="55" /><ent r="3" t="984" w="57" /><ent r="3" t="984" w="57" /><ent r="3" t="1094" w="54" /><ent r="3" t="1094" w="54" /><ent r="7" t="1096" w="57" /><ent r="7" t="1096" w="57" /><ent r="3" t="1145" w="73" /><ent r="3" t="1145" w="73" /><ent r="3" t="1145" w="226" /><ent r="3" t="1145" w="226" /><ent r="5" t="1147" w="55" /><ent r="5" t="1147" w="55" /><ent r="3" t="1679" w="18" /><ent r="3" t="1679" w="18" /><ent r="1000" t="1810" w="2" /><ent r="1000" t="1810" w="2" /><ent r="92" t="1810" w="17" /><ent r="92" t="1810" w="17" /><ent r="1000" t="1991" w="2" /><ent r="1000" t="1991" w="2" /><ent r="92" t="1991" w="12" /><ent r="92" t="1991" w="12" /><ent r="3" t="2139" w="20" /><ent r="3" t="2139" w="20" /><ent r="3" t="2160" w="55" /><ent r="3" t="2160" w="55" /><ent r="3" t="2540" w="62" /><ent r="3" t="2540" w="62" /><ent r="1000" t="2600" w="1" /><ent r="1000" t="2600" w="1" /><ent r="100" t="2600" w="4" /><ent r="100" t="2600" w="4" /><ent r="102" t="2600" w="7" /><ent r="102" t="2600" w="7" /><ent r="3" t="2602" w="16" /><ent r="3" t="2602" w="16" /><ent r="1000" t="2618" w="4" /><ent r="1000" t="2618" w="4" /><ent r="100" t="2618" w="7" /><ent r="100" t="2618" w="7" /><ent r="102" t="2618" w="14" /><ent r="102" t="2618" w="14" /><ent r="7" t="2809" w="139" /><ent r="7" t="2809" w="139" /><ent r="3" t="2973" w="169" /><ent r="3" t="2973" w="169" /><ent r="11" t="2986" w="203" /><ent r="11" t="2986" w="203" /><ent r="3" t="2987" w="146" /><ent r="3" t="2987" w="146" /><ent r="3" t="2992" w="135" /><ent r="3" t="2992" w="135" /><ent r="11" t="3028" w="298" /><ent r="11" t="3028" w="298" /><ent r="1000" t="3037" w="3" /><ent r="1000" t="3037" w="3" /><ent r="100" t="3037" w="8" /><ent r="100" t="3037" w="8" /><ent r="102" t="3037" w="13" /><ent r="102" t="3037" w="13" /><ent r="7" t="3037" w="191" /><ent r="11" t="3101" w="318" /><ent r="11" t="3102" w="277" /><ent r="11" t="3103" w="307" /><ent r="11" t="3104" w="277" /><ent r="5" t="3123" w="48" /><ent r="5" t="3123" w="48" /><ent r="7" t="3124" w="119" /><ent r="7" t="3124" w="119" /></phr><phr n="Controller"><ent r="6" t="1147" w="117" /></phr><phr n="controllers"><ent r="3" t="1876" w="60" /><ent r="3" t="1877" w="67" /><ent r="3" t="1889" w="60" /></phr><phr n="controlling"><ent r="1000" t="2606" w="3" /><ent r="1000" t="2606" w="3" /><ent r="102" t="2606" w="15" /><ent r="102" t="2606" w="15" /></phr></stem><stem n="either"><phr n="either"><ent r="3" t="10" w="348" /><ent r="3" t="10" w="348" /><ent r="3" t="23" w="453" /><ent r="3" t="23" w="453" /><ent r="3" t="23" w="1017" /><ent r="3" t="23" w="1017" /><ent r="3" t="38" w="397" /><ent r="3" t="38" w="397" /><ent r="7" t="72" w="396" /><ent r="7" t="72" w="396" /><ent r="7" t="79" w="113" /><ent r="7" t="79" w="113" /><ent r="3" t="101" w="524" /><ent r="3" t="101" w="524" /><ent r="3" t="101" w="651" /><ent r="3" t="101" w="651" /><ent r="3" t="104" w="91" /><ent r="3" t="104" w="91" /><ent r="3" t="104" w="308" /><ent r="3" t="104" w="308" /><ent r="3" t="118" w="30" /><ent r="3" t="118" w="30" /><ent r="3" t="119" w="27" /><ent r="3" t="119" w="27" /><ent r="3" t="171" w="141" /><ent r="3" t="171" w="141" /><ent r="3" t="312" w="345" /><ent r="3" t="312" w="345" /><ent r="3" t="320" w="339" /><ent r="3" t="320" w="339" /><ent r="3" t="652" w="34" /><ent r="3" t="652" w="34" /><ent r="3" t="671" w="26" /><ent r="3" t="671" w="26" /><ent r="3" t="884" w="29" /><ent r="3" t="884" w="29" /><ent r="3" t="993" w="30" /><ent r="3" t="993" w="30" /><ent r="3" t="1006" w="45" /><ent r="3" t="1006" w="45" /><ent r="3" t="1018" w="37" /><ent r="3" t="1018" w="37" /><ent r="3" t="1026" w="48" /><ent r="3" t="1026" w="48" /><ent r="3" t="1127" w="25" /><ent r="3" t="1127" w="25" /><ent r="3" t="1154" w="60" /><ent r="3" t="1154" w="60" /><ent r="3" t="1224" w="44" /><ent r="3" t="1224" w="44" /><ent r="3" t="1229" w="54" /><ent r="3" t="1229" w="54" /><ent r="3" t="1543" w="52" /><ent r="3" t="1543" w="52" /><ent r="3" t="1570" w="78" /><ent r="3" t="1570" w="78" /><ent r="3" t="1593" w="27" /><ent r="3" t="1593" w="27" /><ent r="3" t="1626" w="24" /><ent r="3" t="1626" w="24" /><ent r="3" t="1721" w="21" /><ent r="3" t="1721" w="21" /><ent r="3" t="1793" w="34" /><ent r="3" t="1793" w="34" /><ent r="3" t="1935" w="25" /><ent r="3" t="1935" w="25" /><ent r="3" t="2240" w="21" /><ent r="3" t="2240" w="21" /><ent r="3" t="2241" w="19" /><ent r="3" t="2241" w="19" /><ent r="6" t="2418" w="60" /><ent r="6" t="2418" w="60" /><ent r="5" t="2418" w="101" /><ent r="5" t="2418" w="101" /><ent r="3" t="2455" w="20" /><ent r="3" t="2455" w="20" /><ent r="3" t="2456" w="45" /><ent r="3" t="2456" w="45" /><ent r="3" t="2470" w="28" /><ent r="3" t="2470" w="28" /><ent r="3" t="2470" w="62" /><ent r="3" t="2470" w="62" /><ent r="7" t="2584" w="193" /><ent r="7" t="2584" w="193" /><ent r="3" t="2658" w="67" /><ent r="3" t="2658" w="67" /><ent r="3" t="2819" w="259" /><ent r="3" t="2819" w="259" /><ent r="3" t="2912" w="45" /><ent r="3" t="2912" w="45" /><ent r="3" t="2913" w="42" /><ent r="3" t="2913" w="42" /><ent r="3" t="2913" w="118" /><ent r="3" t="2913" w="118" /><ent r="3" t="2915" w="80" /><ent r="3" t="2915" w="80" /><ent r="3" t="2917" w="30" /><ent r="3" t="2917" w="30" /><ent r="6" t="2932" w="128" /><ent r="6" t="2932" w="128" /><ent r="3" t="2935" w="122" /><ent r="5" t="3006" w="180" /><ent r="5" t="3006" w="180" /><ent r="3" t="3058" w="75" /><ent r="3" t="3058" w="75" /><ent r="3" t="3059" w="96" /><ent r="3" t="3059" w="96" /><ent r="3" t="3060" w="96" /><ent r="3" t="3060" w="96" /><ent r="3" t="3130" w="78" /><ent r="3" t="3130" w="78" /></phr><phr n="Either"><ent r="1000" t="450" w="2" /><ent r="1000" t="450" w="2" /><ent r="92" t="450" w="20" /><ent r="92" t="450" w="20" /><ent r="1000" t="531" w="2" /><ent r="1000" t="531" w="2" /><ent r="92" t="531" w="23" /><ent r="92" t="531" w="23" /><ent r="3" t="929" w="45" /><ent r="3" t="929" w="45" /><ent r="3" t="1225" w="33" /><ent r="3" t="1225" w="33" /><ent r="3" t="1341" w="17" /><ent r="3" t="1341" w="17" /><ent r="3" t="1371" w="32" /><ent r="3" t="1371" w="32" /><ent r="3" t="1388" w="27" /><ent r="3" t="1388" w="27" /><ent r="3" t="1409" w="19" /><ent r="3" t="1409" w="19" /><ent r="3" t="1597" w="28" /><ent r="3" t="1597" w="28" /><ent r="3" t="1732" w="19" /><ent r="3" t="1732" w="19" /><ent r="3" t="1819" w="111" /><ent r="3" t="1819" w="111" /><ent r="3" t="1927" w="23" /><ent r="3" t="1927" w="23" /><ent r="3" t="1928" w="23" /><ent r="3" t="1928" w="23" /><ent r="3" t="1950" w="19" /><ent r="3" t="1950" w="19" /><ent r="1000" t="1952" w="2" /><ent r="1000" t="1952" w="2" /><ent r="92" t="1952" w="14" /><ent r="92" t="1952" w="14" /><ent r="3" t="1957" w="42" /><ent r="3" t="1957" w="42" /><ent r="3" t="2351" w="38" /><ent r="3" t="2351" w="38" /><ent r="3" t="2363" w="15" /><ent r="3" t="2363" w="15" /><ent r="3" t="2388" w="37" /><ent r="3" t="2388" w="37" /><ent r="3" t="2405" w="27" /><ent r="3" t="2405" w="27" /><ent r="7" t="2732" w="86" /><ent r="7" t="2732" w="86" /><ent r="8" t="2834" w="21" /><ent r="8" t="2834" w="21" /><ent r="7" t="2872" w="168" /><ent r="7" t="2872" w="168" /><ent r="7" t="2873" w="125" /><ent r="7" t="2873" w="125" /><ent r="7" t="2874" w="163" /><ent r="7" t="2874" w="163" /><ent r="7" t="2875" w="123" /><ent r="7" t="2875" w="123" /><ent r="7" t="2876" w="171" /><ent r="7" t="2876" w="171" /><ent r="7" t="2877" w="162" /><ent r="7" t="2877" w="162" /><ent r="7" t="2901" w="156" /><ent r="7" t="2901" w="156" /><ent r="7" t="2907" w="156" /><ent r="7" t="2907" w="156" /></phr></stem><stem n="length"><phr n="length"><ent r="6" t="10" w="389" /><ent r="6" t="10" w="389" /><ent r="3" t="70" w="110" /><ent r="7" t="80" w="729" /><ent r="7" t="80" w="729" /><ent r="3" t="154" w="274" /><ent r="3" t="154" w="274" /><ent r="3" t="182" w="302" /><ent r="3" t="182" w="302" /><ent r="3" t="189" w="21" /><ent r="3" t="189" w="21" /><ent r="3" t="190" w="36" /><ent r="3" t="191" w="196" /><ent r="3" t="191" w="196" /><ent r="3" t="191" w="199" /><ent r="3" t="191" w="199" /><ent r="7" t="193" w="158" /><ent r="7" t="193" w="158" /><ent r="7" t="193" w="166" /><ent r="7" t="193" w="166" /><ent r="1000" t="560" w="4" /><ent r="1000" t="560" w="4" /><ent r="92" t="560" w="17" /><ent r="92" t="560" w="17" /><ent r="3" t="560" w="27" /><ent r="3" t="560" w="27" /><ent r="3" t="560" w="45" /><ent r="3" t="560" w="45" /><ent r="3" t="560" w="53" /><ent r="3" t="560" w="53" /><ent r="3" t="561" w="23" /><ent r="3" t="561" w="23" /><ent r="3" t="561" w="41" /><ent r="3" t="561" w="41" /><ent r="3" t="561" w="49" /><ent r="3" t="561" w="49" /><ent r="1000" t="563" w="4" /><ent r="1000" t="563" w="4" /><ent r="92" t="563" w="17" /><ent r="92" t="563" w="17" /><ent r="1000" t="564" w="4" /><ent r="1000" t="564" w="4" /><ent r="92" t="564" w="17" /><ent r="92" t="564" w="17" /><ent r="1000" t="583" w="3" /><ent r="1000" t="583" w="3" /><ent r="92" t="583" w="16" /><ent r="92" t="583" w="16" /><ent r="3" t="587" w="20" /><ent r="3" t="587" w="20" /><ent r="3" t="587" w="29" /><ent r="1000" t="653" w="4" /><ent r="1000" t="653" w="4" /><ent r="92" t="653" w="11" /><ent r="92" t="653" w="11" /><ent r="3" t="819" w="41" /><ent r="3" t="819" w="41" /><ent r="3" t="1125" w="21" /><ent r="3" t="1125" w="21" /><ent r="3" t="1125" w="29" /><ent r="3" t="1125" w="29" /><ent r="3" t="1169" w="63" /><ent r="3" t="1175" w="40" /><ent r="3" t="1175" w="40" /><ent r="1000" t="1210" w="3" /><ent r="1000" t="1210" w="3" /><ent r="92" t="1210" w="12" /><ent r="92" t="1210" w="12" /><ent r="3" t="1210" w="32" /><ent r="3" t="1210" w="32" /><ent r="1000" t="1211" w="4" /><ent r="1000" t="1211" w="4" /><ent r="92" t="1211" w="14" /><ent r="92" t="1211" w="14" /><ent r="3" t="1211" w="52" /><ent r="3" t="1211" w="52" /><ent r="3" t="1212" w="59" /><ent r="3" t="1212" w="59" /><ent r="3" t="1214" w="60" /><ent r="3" t="1214" w="60" /><ent r="3" t="1220" w="21" /><ent r="3" t="1220" w="21" /><ent r="3" t="1350" w="46" /><ent r="3" t="1350" w="46" /><ent r="3" t="1350" w="72" /><ent r="3" t="1411" w="31" /><ent r="3" t="1411" w="31" /><ent r="3" t="1411" w="39" /><ent r="3" t="1413" w="29" /><ent r="3" t="1413" w="29" /><ent r="3" t="1413" w="40" /><ent r="3" t="1414" w="29" /><ent r="3" t="1414" w="29" /><ent r="3" t="1414" w="40" /><ent r="3" t="1786" w="27" /><ent r="3" t="1788" w="27" /><ent r="3" t="1790" w="24" /><ent r="3" t="1790" w="24" /><ent r="3" t="1790" w="40" /><ent r="3" t="1790" w="40" /><ent r="3" t="1806" w="27" /><ent r="3" t="1806" w="27" /><ent r="3" t="1819" w="17" /><ent r="3" t="1819" w="17" /><ent r="7" t="2363" w="32" /><ent r="7" t="2363" w="32" /><ent r="6" t="2363" w="38" /><ent r="6" t="2363" w="38" /><ent r="6" t="2363" w="51" /><ent r="6" t="2363" w="51" /><ent r="6" t="2363" w="57" /><ent r="6" t="2363" w="57" /><ent r="7" t="2649" w="343" /><ent r="7" t="2649" w="377" /><ent r="7" t="2649" w="377" /><ent r="7" t="2649" w="393" /><ent r="7" t="2649" w="393" /><ent r="7" t="2650" w="48" /><ent r="7" t="2650" w="48" /><ent r="7" t="2650" w="85" /><ent r="7" t="2650" w="85" /><ent r="7" t="2650" w="102" /><ent r="7" t="2650" w="102" /><ent r="7" t="2674" w="348" /><ent r="7" t="2674" w="382" /><ent r="7" t="2674" w="382" /><ent r="7" t="2674" w="398" /><ent r="7" t="2674" w="398" /><ent r="7" t="2675" w="48" /><ent r="7" t="2675" w="48" /><ent r="7" t="2675" w="85" /><ent r="7" t="2675" w="85" /><ent r="7" t="2675" w="102" /><ent r="7" t="2675" w="102" /><ent r="7" t="2686" w="48" /><ent r="7" t="2686" w="48" /><ent r="7" t="2686" w="85" /><ent r="7" t="2686" w="85" /><ent r="7" t="2686" w="102" /><ent r="7" t="2686" w="102" /><ent r="3" t="2687" w="28" /><ent r="3" t="2687" w="28" /><ent r="7" t="2697" w="48" /><ent r="7" t="2697" w="48" /><ent r="7" t="2697" w="85" /><ent r="7" t="2697" w="85" /><ent r="7" t="2697" w="102" /><ent r="7" t="2697" w="102" /><ent r="3" t="2698" w="28" /><ent r="3" t="2698" w="28" /><ent r="7" t="2713" w="43" /><ent r="7" t="2713" w="43" /><ent r="7" t="2727" w="46" /><ent r="7" t="2727" w="46" /><ent r="3" t="2973" w="324" /><ent r="3" t="2973" w="324" /><ent r="3" t="3072" w="59" /><ent r="3" t="3072" w="59" /><ent r="3" t="3072" w="62" /><ent r="7" t="3080" w="162" /><ent r="7" t="3080" w="162" /><ent r="7" t="3082" w="241" /><ent r="7" t="3082" w="241" /><ent r="7" t="3162" w="51" /><ent r="7" t="3162" w="51" /></phr><phr n="lengths"><ent r="3" t="572" w="39" /><ent r="3" t="572" w="39" /><ent r="9" t="824" w="140" /><ent r="9" t="824" w="140" /><ent r="9" t="825" w="144" /><ent r="9" t="825" w="144" /><ent r="1000" t="1175" w="4" /><ent r="1000" t="1175" w="4" /><ent r="92" t="1175" w="17" /><ent r="92" t="1175" w="17" /><ent r="3" t="1175" w="38" /><ent r="3" t="1210" w="30" /><ent r="3" t="1211" w="23" /><ent r="3" t="1211" w="50" /><ent r="3" t="1212" w="57" /><ent r="6" t="2363" w="77" /><ent r="6" t="2363" w="77" /><ent r="3" t="2660" w="76" /><ent r="3" t="2660" w="76" /></phr><phr n="Length"><ent r="7" t="2649" w="339" /><ent r="7" t="2649" w="339" /><ent r="7" t="2649" w="345" /><ent r="7" t="2649" w="345" /><ent r="7" t="2649" w="363" /><ent r="7" t="2649" w="363" /><ent r="7" t="2649" w="366" /><ent r="7" t="2649" w="366" /><ent r="7" t="2650" w="44" /><ent r="7" t="2650" w="44" /><ent r="7" t="2650" w="51" /><ent r="7" t="2650" w="51" /><ent r="7" t="2650" w="70" /><ent r="7" t="2650" w="70" /><ent r="7" t="2650" w="73" /><ent r="7" t="2650" w="73" /><ent r="7" t="2651" w="49" /><ent r="7" t="2651" w="49" /><ent r="7" t="2651" w="52" /><ent r="7" t="2651" w="52" /><ent r="7" t="2651" w="66" /><ent r="7" t="2651" w="66" /><ent r="7" t="2674" w="344" /><ent r="7" t="2674" w="344" /><ent r="7" t="2674" w="350" /><ent r="7" t="2674" w="350" /><ent r="7" t="2674" w="368" /><ent r="7" t="2674" w="368" /><ent r="7" t="2674" w="371" /><ent r="7" t="2674" w="371" /><ent r="7" t="2675" w="44" /><ent r="7" t="2675" w="44" /><ent r="7" t="2675" w="51" /><ent r="7" t="2675" w="51" /><ent r="7" t="2675" w="70" /><ent r="7" t="2675" w="70" /><ent r="7" t="2675" w="73" /><ent r="7" t="2675" w="73" /><ent r="7" t="2676" w="49" /><ent r="7" t="2676" w="49" /><ent r="7" t="2676" w="52" /><ent r="7" t="2676" w="52" /><ent r="7" t="2676" w="66" /><ent r="7" t="2676" w="66" /><ent r="7" t="2686" w="44" /><ent r="7" t="2686" w="44" /><ent r="7" t="2686" w="51" /><ent r="7" t="2686" w="51" /><ent r="7" t="2686" w="70" /><ent r="7" t="2686" w="70" /><ent r="7" t="2686" w="73" /><ent r="7" t="2686" w="73" /><ent r="7" t="2687" w="50" /><ent r="7" t="2687" w="50" /><ent r="7" t="2687" w="53" /><ent r="7" t="2687" w="53" /><ent r="7" t="2687" w="67" /><ent r="7" t="2687" w="67" /><ent r="7" t="2697" w="44" /><ent r="7" t="2697" w="44" /><ent r="7" t="2697" w="51" /><ent r="7" t="2697" w="51" /><ent r="7" t="2697" w="70" /><ent r="7" t="2697" w="70" /><ent r="7" t="2697" w="73" /><ent r="7" t="2697" w="73" /><ent r="7" t="2698" w="50" /><ent r="7" t="2698" w="50" /><ent r="7" t="2698" w="53" /><ent r="7" t="2698" w="53" /><ent r="7" t="2698" w="67" /><ent r="7" t="2698" w="67" /><ent r="7" t="2713" w="39" /><ent r="7" t="2713" w="39" /><ent r="7" t="2713" w="46" /><ent r="7" t="2713" w="46" /><ent r="7" t="2727" w="42" /><ent r="7" t="2727" w="42" /><ent r="7" t="2727" w="49" /><ent r="7" t="2727" w="49" /><ent r="3" t="2973" w="305" /><ent r="3" t="2973" w="305" /><ent r="7" t="3134" w="9" /><ent r="7" t="3134" w="9" /><ent r="7" t="3162" w="47" /><ent r="7" t="3162" w="47" /><ent r="7" t="3162" w="54" /><ent r="7" t="3162" w="54" /></phr></stem></index>