{
   "minVersion":"0.1",
   "headerImage":"https://anhutc.github.io/Banners/AirawBanner.png",
   "tintColor":"#2d3e50",
   "tabs":[
      {
         "tabname":"Details",
         "views":[
            {
                "itemCornerRadius":9,
                "itemSize":"{200,400}",
                "screenshots":[
                    {
                        "accessibilityText":"Screenshot",
                        "url":"https://anhutc.github.io/icons/Airaw/demo.png",
                        "fullSizeURL":"https://anhutc.github.io/icons/Airaw/demo.png"
                    },
                    {
                     "accessibilityText":"Screenshot",
                     "url":"https://anhutc.github.io/icons/Airaw/demo1.png",
                     "fullSizeURL":"https://anhutc.github.io/icons/Airaw/demo1.png"
                     },
                     {
                        "accessibilityText":"Screenshot",
                        "url":"https://anhutc.github.io/icons/Airaw/demo2.png",
                        "fullSizeURL":"https://anhutc.github.io/icons/Airaw/demo2.png"
                    }

                ],
                "class":"DepictionScreenshotsView"
            },
            {
               "class":"DepictionSeparatorView"
            },

            {
                "title":"Features",
                "class":"DepictionHeaderView"
            },
            {
                "class": "DepictionMarkdownView",
                "markdown": "Power action CC Module:",
                "useSpacing": true
            },

            {
                "useBottomMargin": false,
                "markdown": "- respring\n- safemode\n- uicache\n- reboot\n- shutdown \n\n\n- NOTE!!! you need to add it first in CONTROL CENTER section in settings!",
                "useBoldText": true,
                "title": "markdown-description",
                "class": "DepictionMarkdownView"
            },


                            {
                               "title":"What's New",
                               "class":"DepictionHeaderView"
                            },

                            {
                                "markdown":"- initial Release",
                                "useSpacing":true,
                                "class":"DepictionMarkdownView"
                            },



            {
               "title":"Information",
               "class":"DepictionHeaderView"
            },
            {
               "title":"Version",
               "text":"0.0.1",
               "class":"DepictionTableTextView"
            },
            {
               "title":"Updated",
               "text":"Apr 28, 2022",
               "class":"DepictionTableTextView"
            },

            {
               "title":"Price",
               "text":"Free",
               "class":"DepictionTableTextView"
            },
            {
               "title":"Compatibility",
               "text":"iOS 11.0 - 14.8",
               "class":"DepictionTableTextView"
            },


            {
               "title":"Support",
               "class":"DepictionHeaderView"
            },
            {
               "title":"Via PayPal",
               "useBoldText": true,
               "action":"https://www.paypal.com/paypalme/hiwajaf",
               "class":"DepictionTableButtonView"
            },

            {
               "title":"Follow @iKarwan",
               "useBoldText": true,
               "action":"https://twitter.com/ikg_hd",
               "class":"DepictionTableButtonView"
            },

            {
               "title":"YouTube Channel",
               "useBoldText": true,
               "action":"https://youtube.com/c/ikghd",
               "class":"DepictionTableButtonView"
            },

            {"class":"DepictionLabelView",
              "text":"iKarwan Tweaks | iKPowercc 0.0.1",
              "textColor":"#999999","fontSize":"10.0",
              "alignment":1,"class":"DepictionStackView",
              "class":"DepictionTabView"
            },

            {
               "spacing":10,
               "class":"DepictionSpacerView"
            }

         ],
         "class":"DepictionStackView"
      }
   ],
   "class":"DepictionTabView"
}
